hlsrelay/__init__.py
hlsrelay-0.0.1.dist-info/DESCRIPTION.rst
hlsrelay-0.0.1.dist-info/METADATA
hlsrelay-0.0.1.dist-info/RECORD
hlsrelay-0.0.1.dist-info/WHEEL
hlsrelay-0.0.1.dist-info/entry_points.txt
hlsrelay-0.0.1.dist-info/metadata.json
hlsrelay-0.0.1.dist-info/top_level.txt
